{"nm":"Liquid loading animation","ddd":0,"h":500,"w":500,"meta":{"g":"LottieFiles Figma v55"},"layers":[{"ty":4,"nm":"Ellipse 1","sr":1,"st":0,"op":330,"ip":0,"hd":false,"ddd":0,"bm":0,"hasMask":false,"td":1,"ao":0,"ks":{"a":{"a":1,"k":[{"o":{"x":0,"y":0},"i":{"x":1,"y":1},"s":[107.5,107.5],"t":0},{"s":[107.5,107.5],"t":180}]},"s":{"a":1,"k":[{"o":{"x":0,"y":0},"i":{"x":1,"y":1},"s":[100,100],"t":0},{"s":[100,100],"t":180}]},"sk":{"a":0,"k":0},"p":{"a":1,"k":[{"o":{"x":0,"y":0},"i":{"x":1,"y":1},"s":[249.5,249.5],"t":0},{"s":[249.5,249.5],"t":180}]},"r":{"a":1,"k":[{"o":{"x":0,"y":0},"i":{"x":1,"y":1},"s":[0],"t":0},{"s":[0],"t":180}]},"sa":{"a":0,"k":0},"o":{"a":1,"k":[{"o":{"x":0,"y":0},"i":{"x":1,"y":1},"s":[100],"t":0},{"s":[100],"t":180}]}},"shapes":[{"ty":"sh","bm":0,"hd":false,"nm":"","d":1,"ks":{"a":1,"k":[{"o":{"x":0,"y":0},"i":{"x":1,"y":1},"s":[{"c":true,"i":[[0,0],[59.37,0],[0,59.37],[-59.37,0],[0,-59.37]],"o":[[0,59.37],[-59.37,0],[0,-59.37],[59.37,0],[0,0]],"v":[[215,107.5],[107.5,215],[0,107.5],[107.5,0],[215,107.5]]}],"t":0},{"s":[{"c":true,"i":[[0,0],[59.37,0],[0,59.37],[-59.37,0],[0,-59.37]],"o":[[0,59.37],[-59.37,0],[0,-59.37],[59.37,0],[0,0]],"v":[[215,107.5],[107.5,215],[0,107.5],[107.5,0],[215,107.5]]}],"t":180}]}},{"ty":"fl","bm":0,"hd":false,"nm":"","c":{"a":1,"k":[{"o":{"x":0,"y":0},"i":{"x":1,"y":1},"s":[0.851,0.851,0.851],"t":0},{"s":[0.851,0.851,0.851],"t":180}]},"r":1,"o":{"a":1,"k":[{"o":{"x":0,"y":0},"i":{"x":1,"y":1},"s":[100],"t":0},{"s":[100],"t":180}]}}],"ind":1},{"ty":4,"nm":"Vector 1","sr":1,"st":0,"op":330,"ip":0,"hd":false,"ddd":0,"bm":0,"tt":1,"hasMask":false,"ao":0,"ks":{"a":{"a":1,"k":[{"o":{"x":0,"y":0},"i":{"x":1,"y":1},"s":[710.86,128.75],"t":0},{"s":[710.86,128.75],"t":180}]},"s":{"a":1,"k":[{"o":{"x":0,"y":0},"i":{"x":1,"y":1},"s":[100,100],"t":0},{"s":[100,100],"t":180}]},"sk":{"a":0,"k":0},"p":{"a":1,"k":[{"o":{"x":0,"y":0},"i":{"x":1,"y":1},"s":[-425.64,447.75],"t":0},{"s":[826.36,249.75],"t":180}]},"r":{"a":1,"k":[{"o":{"x":0,"y":0},"i":{"x":1,"y":1},"s":[0],"t":0},{"s":[0],"t":180}]},"sa":{"a":0,"k":0},"o":{"a":1,"k":[{"o":{"x":0,"y":0},"i":{"x":1,"y":1},"s":[100],"t":0},{"s":[100],"t":180}]}},"shapes":[{"ty":"sh","bm":0,"hd":false,"nm":"","d":1,"ks":{"a":1,"k":[{"o":{"x":0,"y":0},"i":{"x":1,"y":1},"s":[{"c":true,"i":[[0,0],[32.86,-31.28],[0,0],[0,0],[-10.97,48.51],[55,0],[64.23,0],[65.72,0],[61.24,0],[61.24,0],[49.29,0],[61.24,0],[67.21,0],[80.66,0]],"o":[[-64.53,0],[0,0],[0,0],[0,0],[9.5,-42],[-55,0],[-64.23,0],[-65.72,0],[-61.24,0],[-61.24,0],[-49.29,0],[-61.24,0],[-67.21,0],[0,0]],"v":[[118,15.5],[0,114],[0,257.5],[1387.5,257.5],[1420.5,134.5],[1328,7],[1183,36.5],[1015.5,0],[849,36.5],[704.5,7],[544.5,36.5],[405.5,15.5],[245.5,36.5],[118,15.5]]}],"t":0},{"s":[{"c":true,"i":[[0,0],[32.86,-31.28],[0,0],[0,0],[-10.97,48.51],[55,0],[64.23,0],[65.72,0],[61.24,0],[61.24,0],[49.29,0],[61.24,0],[67.21,0],[80.66,0]],"o":[[-64.53,0],[0,0],[0,0],[0,0],[9.5,-42],[-55,0],[-64.23,0],[-65.72,0],[-61.24,0],[-61.24,0],[-49.29,0],[-61.24,0],[-67.21,0],[0,0]],"v":[[118,15.5],[0,114],[0,257.5],[1387.5,257.5],[1420.5,134.5],[1328,7],[1183,36.5],[1015.5,0],[849,36.5],[704.5,7],[544.5,36.5],[405.5,15.5],[245.5,36.5],[118,15.5]]}],"t":180}]}},{"ty":"gf","bm":0,"hd":false,"nm":"","e":{"a":1,"k":[{"o":{"x":0,"y":0},"i":{"x":1,"y":1},"s":[678.0059814453125,15.5],"t":0},{"s":[678.0059814453125,15.5],"t":180}]},"g":{"p":3,"k":{"a":1,"k":[{"o":{"x":0,"y":0},"i":{"x":1,"y":1},"s":[0,0.7176862913393507,0.8549411851191053,0.9608235317492018,0.6200000047683716,0.09023529619212245,0.5294510084414015,0.878470595481349,1,0.0823921594047079,0.4784705895208845,0.7921960908197889,0,0.8901960849761963,0.6200000047683716,1,1,1],"t":0},{"s":[0,0.7176862913393507,0.8549411851191053,0.9608235317492018,0.7300000190734863,0.09023529619212245,0.5294510084414015,0.878470595481349,1,0.0823921594047079,0.4784705895208845,0.7921960908197889,0,0.8901960849761963,0.7300000190734863,1,1,1],"t":180}]}},"t":1,"a":{"a":0,"k":0},"h":{"a":0,"k":0},"s":{"a":1,"k":[{"o":{"x":0,"y":0},"i":{"x":1,"y":1},"s":[678.0059814453125,257.5],"t":0},{"s":[678.0059814453125,257.5],"t":180}]},"r":1,"o":{"a":1,"k":[{"o":{"x":0,"y":0},"i":{"x":1,"y":1},"s":[100],"t":0},{"s":[100],"t":180}]}}],"ind":2},{"ty":"fl","bm":0,"hd":false,"nm":"","c":{"a":1,"k":[{"o":{"x":0,"y":0},"i":{"x":1,"y":1},"s":[0,0,0],"t":0},{"s":[0,0,0],"t":180}]},"r":1,"o":{"a":1,"k":[{"o":{"x":0,"y":0},"i":{"x":1,"y":1},"s":[0],"t":0},{"s":[0],"t":180}]}}],"v":"5.7.0","fr":30,"op":330,"ip":0,"assets":[]}]}